manic/Baseline.py
manic/Crossover.py
manic/Disagreement.py
manic/Evaluation.py
manic/Fitness.py
manic/GeneticAlgorithm.py
manic/Initialise.py
manic/Manic.py
manic/Mutation.py
manic/Replacement.py
manic/Selection.py
manic/Termination.py
manic/Utility.py
manic/__init__.py
manic/test.py
manic/__tests__/__init__.py
manic/__tests__/test_attributes.py
manic/__tests__/test_baseline.py
manic/__tests__/test_crossover.py
manic/__tests__/test_disagreement.py
manic/__tests__/test_evaluation.py
manic/__tests__/test_genetic_algorithm.py
manic/__tests__/test_initialise.py
manic/__tests__/test_initialise_population.py
manic/__tests__/test_manic.py
manic/__tests__/test_manic_reproducibility.py
manic/__tests__/test_mutation.py
manic/__tests__/test_replacement.py
manic/__tests__/test_selection.py
manic/__tests__/test_termination.py
manic/__tests__/test_utility.py
manic/__tests__/test_validity.py
manic_xai-1.0.83.dist-info/LICENSE
manic_xai-1.0.83.dist-info/METADATA
manic_xai-1.0.83.dist-info/WHEEL
manic_xai-1.0.83.dist-info/top_level.txt
manic_xai-1.0.83.dist-info/RECORD
