Metadata-Version: 2.1
Name: manic-xai
Version: 1.0.83
Summary: Genetic Algorithm for Generating Metacounterfactual Explanations
Home-page: https://github.com/craigybaeb/MANIC
Author: Craig Pirie
Author-email: c.pirie11@rgu.ac.uk
Keywords: manic,metacounterfactual,counterfactual,xai,explanation,aggregation,disagreement,agreement
Classifier: Programming Language :: Python :: 3
Classifier: License :: OSI Approved :: MIT License
Classifier: Operating System :: OS Independent
License-File: LICENSE
Requires-Dist: matplotlib (>=3.4.3)
Requires-Dist: numpy (>=1.21.2)
Requires-Dist: scikit-learn (>=0.24.2)
Requires-Dist: seaborn (>=0.11.2)
